genoray/__init__.py
genoray/_pgen.py
genoray/_svar.py
genoray/_types.py
genoray/_utils.py
genoray/_var_ranges.py
genoray/_vcf.py
genoray/exprs.py
genoray/py.typed
genoray-1.0.1.dist-info/METADATA
genoray-1.0.1.dist-info/WHEEL
genoray-1.0.1.dist-info/licenses/LICENSE.txt
genoray-1.0.1.dist-info/RECORD
