Metadata-Version: 2.4
Name: genoray
Version: 1.0.1
Summary: Add your description here
Author-email: David Laub <dlaub@ucsd.edu>
License: Copyright (c) 2025 David Laub
License-File: LICENSE.txt
Requires-Python: <3.13,>=3.9
Requires-Dist: attrs
Requires-Dist: awkward
Requires-Dist: cyclopts
Requires-Dist: cyvcf2>=0.31.1
Requires-Dist: genoray>=0.15.0
Requires-Dist: hirola>=0.3.0
Requires-Dist: loguru>=0.7.0
Requires-Dist: more-itertools>=10
Requires-Dist: numba
Requires-Dist: numpy>=1.26
Requires-Dist: pandas>=2.2.2
Requires-Dist: pgenlib>=0.91.0
Requires-Dist: phantom-types>=3
Requires-Dist: polars-bio>=0.19.0
Requires-Dist: polars>=1.30
Requires-Dist: pyarrow>=21
Requires-Dist: pydantic
Requires-Dist: pyranges>=0.1.3
Requires-Dist: seqpro>=0.8.0
Requires-Dist: tqdm>=4.65
Requires-Dist: typing-extensions>=4.11
Requires-Dist: zstandard
Provides-Extra: cli
Requires-Dist: genoray-cli>=0.1.2; extra == 'cli'
